fifo.v
`timescale 1ns / 1ns

module fifo(clk, data_in, rd, wr, en, data_out, rst, empty, full, seq, tim_out, rdy,num_packets_to_replay, replay_index ); 

input  clk, wr, en, rst, tim_out;

input [1:0] rd;

input [11:0] seq, replay_index;

output  empty, full;

input   [15:0]    data_in;

output reg [15:0] data_out; // internal registers 

output reg rdy;

reg [11:0] last_seq_written = 0;

output reg [11:0] num_packets_to_replay;

reg [11:0]  count = 0; 

reg [15:0] FIFO [0:4095];                     

reg [11:0]      read_counter = 0, 
                write_counter = 0; 
				
		

assign empty = (count==0)? 1'b1:1'b0; 

assign full = (count==4096)? 1'b1:1'b0; 

always @ (posedge clk) 

begin 

if (!en); //if enable is low, do nothing

else 
	begin 
		if (rst) //reset and initialize 
			begin 
				data_out = 0;
				read_counter = 0; 
				write_counter = 0;
				rdy = 1; 
			end
		


		else // no reset or time-out
			begin
				// receiver sends ack, advance rd pointer past sequence number transmitted 
				// with DLLP to purged replay buffer of received packets
				if(rd == 2'b01 && count != 0 && !wr) 	
					begin
						read_counter = read_counter + seq;
						rdy = 0;
					end
				// receiver sends NACK DLLP, retransmit all TLP in buffer with EARLIER
				//sequence number than seq[11:0] supplied with NACK DLLP
				else if ( (tim_out || rd == 2'b10) && count != 0 && !wr ) 											
					begin
						read_counter = read_counter + (seq * 10);
						
						num_packets_to_replay = ((last_seq_written - seq)*10) -1;
					end							
				else if (rep && !wr)
					begin
						data_out = FIFO[read_counter + replay_index];
					end
				
				else if (wr==1'b1 && count<4096) 
					
					begin
						FIFO[write_counter]  = data_in; 	   
						write_counter  = write_counter + seq; 	
						last_seq_written = last_seq_written + 1;
					end 

				if (write_counter == 4096) 
					write_counter = 0; 

				else if (read_counter == 4096) 
					read_counter = 0; 

				if (read_counter > write_counter) 
					count = read_counter - write_counter; 

				else if (write_counter > read_counter) 
					count = write_counter - read_counter; 
				
				if(full)
					rdy = 0;
			end
	end		
end 

endmodule

fifo_tb.v
`timescale 1ns / 1ps

module fifo_tb;

 // Inputs

 reg clk;

 reg [15:0] data_in;

 reg [1:0] rd;

 reg wr;

 reg en;

 reg rst;

 reg tim_out, rep;

 // Outputs

 wire [15:0] data_out;

 wire rdy;

 wire [11:0] num_packets_to_replay;

 wire empty;

 wire full;                                                                                                                                                                                         

 // Instantiate the Unit Under Test (UUT)

 fifo uut (clk, data_in, rd, wr, en, data_out, rst, empty, full, seq, tim_out, rdy,num_packets_to_replay, replay_index, rep);

 initial begin

  // Initialize Inputs

   clk  = 1'b0;

   data_in  = 16'h0;

   rd  = 1'b0;

   wr  = 1'b0;

   en  = 1'b0;

   rst  = 1'b1;

   // Wait 100 ns for global reset to finish

   #100;        

   // Add stimulus here

   en  = 1'b1;

   rst  = 1'b1;

   #20;

   rst  = 1'b0;

   wr  = 1'b1;

   data_in  = 16'h0;

   #20;

   data_in  = 16'h1;

   #20;

   data_in  = 16'h2;

   #20;

   data_in  = 16'h3;

   #20;

   data_in  = 16'h4;

   #20;

   wr = 1'b0;

   rd = 2'b10; //nack
   #100;

   end 

   always #10 clk = ~clk;    

// Run simulation for 500 ns.  
   initial #500 $finish;
   
   // Dump all waveforms to fifo.vcd
   initial
      begin
                  $dumpfile("fifo.vcd");
	$dumpvars(0, fifo_tb);	 
      end // initial begin
   
   initial 
      $monitor ($time, "ns, data_in=%H, data_out=%h, rd=%h, wr=%h, en=%h, rst=%h",data_in, data_out, rd,wr, en, rst);
   
  
   

   
endmodule

fifo.vcd
$date
	Fri May  8 13:49:22 2020
$end

$version
	Synopsys VCS version O-2018.09-SP2-3_Full64
$end

$timescale
	1ps
$end

$comment Csum: 1 ad3c588cce271ddb $end


$scope module fifo_tb $end
$var reg 1 ! clk $end
$var reg 16 " data_in [15:0] $end
$var reg 2 # rd [1:0] $end
$var reg 1 $ wr $end
$var reg 1 % en $end
$var reg 1 & rst $end
$var reg 1 ' tim_out $end
$var reg 1 ( rep $end
$var wire 16 ) data_out [15:0] $end
$var wire 1 * rdy $end
$var wire 12 + num_packets_to_replay [11:0] $end
$var wire 1 , empty $end
$var wire 1 - full $end
$var wire 1 . seq $end
$var wire 1 / replay_index $end

$scope module uut $end
$var wire 1 ! clk $end
$var wire 1 $ wr $end
$var wire 1 % en $end
$var wire 1 & rst $end
$var wire 1 0 tim_out $end
$var wire 1 1 rep $end
$var wire 2 # rd [1:0] $end
$var wire 12 2 seq [11:0] $end
$var wire 12 3 replay_index [11:0] $end
$var wire 1 , empty $end
$var wire 1 - full $end
$var wire 16 " data_in [15:0] $end
$var reg 16 ) data_out [15:0] $end
$var reg 1 * rdy $end
$var reg 12 4 last_seq_written [11:0] $end
$var reg 12 + num_packets_to_replay [11:0] $end
$var reg 12 5 count [11:0] $end
$var reg 12 6 read_counter [11:0] $end
$var reg 12 7 write_counter [11:0] $end
$upscope $end

$upscope $end

$enddefinitions $end

#0
$dumpvars
0!
0%
0-
z/
1&
z.
x,
x*
0$
b000000000000 5
b0000000000000000 "
bxxxxxxxxxxxxxxxx )
b000000000001 4
b000000000000 +
b00 #
b000000000001 6
bxxxxxxxxxxxx 2
bxxxxxxxxxxxx 3
b000000000001 7
x1
x0
x(
x'
$end
b00000000000z 2
b00000000000z 3
1,
#10000
1!
#20000
0!
#30000
1!
#40000
0!
#50000
1!
#60000
0!
#70000
1!
#80000
0!
#90000
1!
#100000
1%
0!
#110000
1!
b0000000000000000 )
1*
#120000
0&
1$
0!
#130000
1!
b000000000010 7
b000000000001 5
0,
#140000
b0000000000000001 "
0!
#150000
1!
b000000000011 7
b000000000010 5
#160000
b0000000000000010 "
0!
#170000
1!
b000000000100 7
b000000000011 5
#180000
b0000000000000011 "
0!
#190000
1!
b000000000101 7
b000000000100 5
#200000
b0000000000000100 "
0!
#210000
1!
b000000000110 7
b000000000101 5
#220000
0$
b10 #
0!
#230000
1!
bxxxxxxxxxxxx 6
bxxxxxxxxxxxx +
