MUX10.v
module mux10(d0, d1, d2, d3, d4, d5, d6, d7, d8, d9, s, y);
input[15:0]  d0, d1, d2, d3, d4, d5, d6, d7, d8, d9;
input[3:0]   s;
output[15:0] y;
reg[15:0]    y;

always @(d0 or d1 or d2 or d3 or d4 or d5 or d6 or d7 or d8 or d9 or s)
begin
  case(s)
  4'b0000: y = d0;
  4'b0001: y = d1;
  4'b0010: y = d2;
  4'b0011: y = d3;
  4'b0100: y = d4;
  4'b0101: y = d5;
  4'b0110: y = d6;
  4'b0111: y = d7;
  4'b1000: y = d8;
  4'b1001: y = d9;

  default: y = d0;
 endcase
end
endmodule

MUX10_tb.v
module MUX10_tb;
reg[15:0]  d0, d1, d2, d3, d4, d5, d6, d7, d8, d9;
reg[3:0]   s;
wire[15:0] y;

mux10 u1 (d0, d1, d2, d3, d4, d5, d6, d7, d8, d9, s, y);
initial 
    begin
        d0 = 16'h000A;
        d1 = 16'h000B;
        d2 = 16'h000C;
        d3 = 16'h000D;
        d4 = 16'h000E;
        d5 = 16'h000F;
        d6 = 16'h0001;
        d7 = 16'h0002;
        d8 = 16'h0003;
        d9 = 16'h0004;
        s = 4'h0;
        #5 s = 4'h1;
        #5 s = 4'h2;
        #5 s = 4'h3;
        #5 s = 4'h4;
        #5 s = 4'h5;
        #5 s = 4'h6;
        #5 s = 4'h7;
        #5 s = 4'h8;
        #5 s = 4'h9;
        #10 $stop;
    end

initial 
    begin
		$dumpfile("MUX10.vcd");
		$dumpvars(0, MUX10_tb);
	end
endmodule

MUX10.vcd
$date
	Fri May  8 12:49:17 2020
$end

$version
	Synopsys VCS version O-2018.09-SP2-3_Full64
$end

$timescale
	1s
$end

$comment Csum: 1 873b73e0b5785273 $end


$scope module MUX10_tb $end
$var reg 16 ! d0 [15:0] $end
$var reg 16 " d1 [15:0] $end
$var reg 16 # d2 [15:0] $end
$var reg 16 $ d3 [15:0] $end
$var reg 16 % d4 [15:0] $end
$var reg 16 & d5 [15:0] $end
$var reg 16 ' d6 [15:0] $end
$var reg 16 ( d7 [15:0] $end
$var reg 16 ) d8 [15:0] $end
$var reg 16 * d9 [15:0] $end
$var reg 4 + s [3:0] $end
$var wire 16 , y [15:0] $end

$scope module u1 $end
$var wire 16 ! d0 [15:0] $end
$var wire 16 " d1 [15:0] $end
$var wire 16 # d2 [15:0] $end
$var wire 16 $ d3 [15:0] $end
$var wire 16 % d4 [15:0] $end
$var wire 16 & d5 [15:0] $end
$var wire 16 ' d6 [15:0] $end
$var wire 16 ( d7 [15:0] $end
$var wire 16 ) d8 [15:0] $end
$var wire 16 * d9 [15:0] $end
$var wire 4 + s [3:0] $end
$var reg 16 , y [15:0] $end
$upscope $end

$upscope $end

$enddefinitions $end

#0
$dumpvars
b0000000000001010 !
b0000000000001011 "
b0000000000001100 #
b0000000000001101 $
b0000000000001110 %
b0000000000001111 &
b0000000000000001 '
b0000000000000010 (
b0000000000000011 )
b0000000000000100 *
b0000 +
b0000000000001010 ,
$end
#5
b0001 +
b0000000000001011 ,
#10
b0010 +
b0000000000001100 ,
#15
b0011 +
b0000000000001101 ,
#20
b0100 +
b0000000000001110 ,
#25
b0101 +
b0000000000001111 ,
#30
b0110 +
b0000000000000001 ,
#35
b0111 +
b0000000000000010 ,
#40
b1000 +
b0000000000000011 ,
#45
b1001 +
b0000000000000100 ,
